Metadata-Version: 2.1
Name: invoicing-generator
Version: 1.0.0
Summary: This package is used to convert Excel files to PDF format.
Home-page: https://nancychaudhry.com/
Author: Nancy Chaudhry
Author-email: chaudhrynancyann@gmail.com
License: MIT
Keywords: invoice,excel,pdf,generator
Classifier: Development Status :: 3 - Alpha
Classifier: Intended Audience :: Developers
Classifier: Topic :: Software Development :: Build Tools
Classifier: License :: OSI Approved :: MIT License
Classifier: Programming Language :: Python :: 3.8
Classifier: Programming Language :: Python :: 3.9
Classifier: Programming Language :: Python :: 3.10
Classifier: Programming Language :: Python :: 3.11
Classifier: Programming Language :: Python :: 3.12
Requires-Dist: pandas
Requires-Dist: fpdf
Requires-Dist: openpyxl
